demos/rf_fund.py
demos/rsi_single.py
tests/test_automl.py
tests/test_causal.py
tests/test_derive.py
tests/test_evaluate.py
tests/test_examine.py
tests/test_explore.py
tests/test_query.py
tradelearn/__init__.py
tradelearn/automl/__init__.py
tradelearn/automl/automl.py
tradelearn/automl/common/lazy_predict.py
tradelearn/causal/blanket/__init__.py
tradelearn/causal/blanket/blanket.py
tradelearn/causal/blanket/pyfeature/condition_independence_test.py
tradelearn/causal/blanket/pyfeature/iamb.py
tradelearn/causal/blanket/pyfeature/pcmb.py
tradelearn/causal/blanket/pyfeature/cit/chi_square_test.py
tradelearn/causal/blanket/pyfeature/cit/fisher_z_test.py
tradelearn/causal/blanket/pyfeature/cit/g2test.py
tradelearn/causal/graph/__init__.py
tradelearn/causal/graph/graph.py
tradelearn/causal/graph/causallearn/ges.py
tradelearn/causal/graph/causallearn/pc.py
tradelearn/causal/graph/causallearn/graph/AdjacencyConfusion.py
tradelearn/causal/graph/causallearn/graph/ArrowConfusion.py
tradelearn/causal/graph/causallearn/graph/Dag.py
tradelearn/causal/graph/causallearn/graph/Edge.py
tradelearn/causal/graph/causallearn/graph/Edges.py
tradelearn/causal/graph/causallearn/graph/Endpoint.py
tradelearn/causal/graph/causallearn/graph/GeneralGraph.py
tradelearn/causal/graph/causallearn/graph/Graph.py
tradelearn/causal/graph/causallearn/graph/GraphClass.py
tradelearn/causal/graph/causallearn/graph/GraphNode.py
tradelearn/causal/graph/causallearn/graph/Node.py
tradelearn/causal/graph/causallearn/graph/NodeType.py
tradelearn/causal/graph/causallearn/graph/NodeVariableType.py
tradelearn/causal/graph/causallearn/graph/SHD.py
tradelearn/causal/graph/causallearn/utils/CIT.py
tradelearn/causal/graph/causallearn/utils/DAG2CPDAG.py
tradelearn/causal/graph/causallearn/utils/GESUtils.py
tradelearn/causal/graph/causallearn/utils/GraphUtils.py
tradelearn/causal/graph/causallearn/utils/PDAG2DAG.py
tradelearn/causal/graph/causallearn/utils/kci/GaussianKernel.py
trade_learn-0.1.1.8.dist-info/METADATA
trade_learn-0.1.1.8.dist-info/WHEEL
trade_learn-0.1.1.8.dist-info/top_level.txt
trade_learn-0.1.1.8.dist-info/RECORD
