Metadata-Version: 2.1
Name: trade-learn
Version: 0.1.1.8
Summary: trade-learn Python Package
Home-page: https://github.com/MuuYesen/trade-learn
Author: 
Classifier: Programming Language :: Python :: 3
Classifier: License :: OSI Approved :: MIT License
Classifier: Operating System :: OS Independent
Requires-Python: >=3.7
Requires-Dist: numpy
Requires-Dist: pandas
Requires-Dist: scipy
Requires-Dist: statsmodels
Requires-Dist: scikit-learn
Requires-Dist: seaborn
Requires-Dist: bokeh
Requires-Dist: yfinance
Requires-Dist: mootdx
Requires-Dist: pydot
Requires-Dist: quantstats
Requires-Dist: htmlmin
